{
  "id": "aef9c9e5-58ff-4eaf-8ee5-129dcd4b2370",
  "generatorId": "f9bf8154-343d-47cf-996a-5c9b70cad61f",
  "metadata": null,
  "name": "german_credit",
  "description": null,
  "generationStatus": "DONE",
  "generationTime": null,
  "tables": [
    {
      "id": "0c9192da-9d45-4181-9294-cd3319fca5fa",
      "name": "data",
      "configuration": {
        "sampleSize": 100,
        "sampleSeedConnectorId": null,
        "sampleSeedDict": null,
        "sampleSeedData": null,
        "samplingTemperature": 1.0,
        "samplingTopP": 1.0,
        "rebalancing": null,
        "imputation": null,
        "fairness": null,
        "enableDataReport": true
      },
      "tabularModelMetrics": {
        "accuracy": {
          "overall": 0.8440758,
          "univariate": 0.9420629,
          "bivariate": 0.8674127,
          "trivariate": 0.7227517,
          "coherence": null,
          "overallMax": 0.8456231,
          "univariateMax": 0.9409995,
          "bivariateMax": 0.8636798,
          "trivariateMax": 0.73219,
          "coherenceMax": null
        },
        "distances": {
          "imsTraining": 0.0,
          "imsHoldout": 0.0,
          "imsTrnHol": 0.0,
          "dcrTraining": 0.504,
          "dcrHoldout": 0.491,
          "dcrTrnHol": 0.477,
          "dcrShare": 0.525,
          "nndrTraining": 0.831742823002,
          "nndrHoldout": 0.835825229632,
          "nndrTrnHol": 0.818495693328
        },
        "similarity": {
          "cosineSimilarityTrainingSynthetic": 0.9717273,
          "cosineSimilarityTrainingHoldout": 0.9587773,
          "discriminatorAUCTrainingSynthetic": 0.39,
          "discriminatorAUCTrainingHoldout": 0.401
        }
      },
      "languageModelMetrics": null,
      "foreignKeys": null,
      "totalRows": 100,
      "totalDatapoints": null,
      "sourceTableTotalRows": 300
    }
  ],
  "delivery": null,
  "accuracy": null,
  "usage": null,
  "compute": null,
  "randomState": null
}