{
    "columns": {
        "limit_amount": {
            "encoding_type": "TABULAR_NUMERIC_BINNED",
            "cardinalities": {
                "bin": 103
            },
            "codes": {
                "<<UNK>>": 0,
                "<<MIN>>": 1,
                "<<MAX>>": 2
            },
            "min_decimal": -2,
            "bins": [
                7688.49,
                9619.74,
                10501.71,
                10894.22,
                12506.02,
                14282.49,
                14692.01,
                16877.52,
                17630.31,
                18758.69,
                20067.37,
                20873.53,
                21984.51,
                23301.54,
                23969.75,
                25732.7,
                26269.09,
                26482.79,
                26975.55,
                27304.26,
                27915.27,
                28266.97,
                28741.08,
                29948.36,
                30646.71,
                30972.55,
                33159.94,
                34735.82,
                34773.17,
                34816.47,
                35548.93,
                36955.77,
                38207.32,
                38809.96,
                39220.57,
                40321.4,
                41733.53,
                42546.16,
                44296.17,
                44403.82,
                44409.17,
                46664.79,
                47467.69,
                47595.08,
                50885.71,
                51429.05,
                51650.88,
                52127.8,
                55073.99,
                56573.46,
                57568.0,
                57881.88,
                59211.98,
                59752.05,
                60272.78,
                60787.32,
                65465.15,
                66810.51,
                69156.17,
                69605.24,
                71868.5,
                73380.93,
                75084.9,
                75866.63,
                76684.78,
                79163.62,
                82839.45,
                84187.61,
                85734.86,
                89094.51,
                93174.77,
                96126.06,
                97196.6,
                97774.97,
                100406.3,
                104154.12,
                107376.91,
                110177.91,
                111148.9,
                113182.21,
                115646.99,
                116021.26,
                119126.95,
                122730.21,
                128309.15,
                130043.36,
                133170.38,
                134917.25,
                136878.39,
                139091.24,
                146234.98,
                151503.57,
                151559.84,
                156618.82,
                161236.79,
                161937.9,
                169119.53,
                173506.15,
                176075.81,
                189590.57,
                190297.09
            ],
            "argn_processor": "tgt",
            "argn_table": "t0",
            "argn_column": "c0"
        },
        "used_amount": {
            "encoding_type": "TABULAR_NUMERIC_BINNED",
            "cardinalities": {
                "bin": 103
            },
            "codes": {
                "<<UNK>>": 0,
                "<<MIN>>": 1,
                "<<MAX>>": 2
            },
            "min_decimal": -2,
            "bins": [
                537.28,
                1979.01,
                2259.49,
                2336.44,
                2553.32,
                2670.52,
                3150.77,
                3159.17,
                3353.29,
                3532.91,
                3616.94,
                3948.1,
                4228.18,
                4580.02,
                4965.09,
                5351.78,
                5651.08,
                5723.48,
                5891.21,
                6777.56,
                7075.41,
                7304.69,
                7455.75,
                8001.52,
                8780.72,
                8874.91,
                9272.98,
                9753.03,
                10068.25,
                10102.85,
                10843.91,
                11168.56,
                12132.06,
                12910.35,
                13087.04,
                13459.87,
                14537.73,
                15263.76,
                15440.1,
                15454.53,
                16016.13,
                16832.17,
                17264.73,
                18140.39,
                18373.06,
                19243.94,
                19444.67,
                19445.84,
                19850.77,
                20017.8,
                20226.38,
                21663.69,
                22926.8,
                25095.35,
                25594.08,
                26101.42,
                26560.16,
                27073.72,
                27095.99,
                27908.53,
                27922.86,
                29728.71,
                30311.86,
                31457.56,
                31576.07,
                33432.25,
                34081.64,
                35149.98,
                36466.64,
                36901.62,
                37550.71,
                37946.2,
                40453.95,
                40836.32,
                41736.47,
                43420.07,
                45076.17,
                49675.65,
                50048.78,
                51470.3,
                53062.15,
                54850.44,
                56261.48,
                57305.23,
                60741.67,
                62765.14,
                64759.21,
                67634.33,
                71114.73,
                77834.38,
                79386.86,
                81083.45,
                82509.51,
                88384.6,
                90828.49,
                95263.89,
                96946.91,
                102410.26,
                110146.89,
                112002.87,
                116272.82
            ],
            "argn_processor": "tgt",
            "argn_table": "t1",
            "argn_column": "c1"
        },
        "customer_id": {
            "encoding_type": "TABULAR_CHARACTER",
            "has_nan": false,
            "max_string_length": 9,
            "codes": {
                "P0": {
                    "\u0000": 0,
                    "C": 1
                },
                "P1": {
                    "\u0000": 0,
                    "U": 1
                },
                "P2": {
                    "\u0000": 0,
                    "S": 1
                },
                "P3": {
                    "\u0000": 0,
                    "1": 1
                },
                "P4": {
                    "\u0000": 0,
                    "0": 1
                },
                "P5": {
                    "\u0000": 0,
                    "0": 1
                },
                "P6": {
                    "\u0000": 0,
                    "0": 1,
                    "1": 2,
                    "2": 3,
                    "3": 4,
                    "4": 5
                },
                "P7": {
                    "\u0000": 0,
                    "0": 1,
                    "1": 2,
                    "2": 3,
                    "3": 4,
                    "4": 5,
                    "5": 6,
                    "6": 7,
                    "7": 8,
                    "8": 9,
                    "9": 10
                },
                "P8": {
                    "\u0000": 0,
                    "0": 1,
                    "1": 2,
                    "2": 3,
                    "3": 4,
                    "4": 5,
                    "5": 6,
                    "6": 7,
                    "7": 8,
                    "8": 9,
                    "9": 10
                }
            },
            "cardinalities": {
                "P0": 2,
                "P1": 2,
                "P2": 2,
                "P3": 2,
                "P4": 2,
                "P5": 2,
                "P6": 6,
                "P7": 11,
                "P8": 11
            },
            "argn_processor": "tgt",
            "argn_table": "t2",
            "argn_column": "c2"
        },
        "account_id": {
            "encoding_type": "TABULAR_CHARACTER",
            "has_nan": false,
            "max_string_length": 9,
            "codes": {
                "P0": {
                    "\u0000": 0,
                    "A": 1
                },
                "P1": {
                    "\u0000": 0,
                    "C": 1
                },
                "P2": {
                    "\u0000": 0,
                    "C": 1
                },
                "P3": {
                    "\u0000": 0,
                    "2": 1
                },
                "P4": {
                    "\u0000": 0,
                    "0": 1
                },
                "P5": {
                    "\u0000": 0,
                    "0": 1,
                    "1": 2
                },
                "P6": {
                    "\u0000": 0,
                    "0": 1,
                    "1": 2,
                    "2": 3,
                    "3": 4,
                    "4": 5,
                    "5": 6,
                    "6": 7,
                    "7": 8,
                    "8": 9,
                    "9": 10
                },
                "P7": {
                    "\u0000": 0,
                    "0": 1,
                    "1": 2,
                    "2": 3,
                    "3": 4,
                    "4": 5,
                    "5": 6,
                    "6": 7,
                    "7": 8,
                    "8": 9,
                    "9": 10
                },
                "P8": {
                    "\u0000": 0,
                    "0": 1,
                    "1": 2,
                    "2": 3,
                    "3": 4,
                    "4": 5,
                    "5": 6,
                    "6": 7,
                    "7": 8,
                    "8": 9,
                    "9": 10
                }
            },
            "cardinalities": {
                "P0": 2,
                "P1": 2,
                "P2": 2,
                "P3": 2,
                "P4": 2,
                "P5": 3,
                "P6": 11,
                "P7": 11,
                "P8": 11
            },
            "argn_processor": "tgt",
            "argn_table": "t3",
            "argn_column": "c3"
        },
        "card_type": {
            "value_protection": true,
            "encoding_type": "TABULAR_CATEGORICAL",
            "no_of_rare_categories": 0,
            "codes": {
                "_RARE_": 0,
                "Mastercard": 1,
                "Troy": 2,
                "Visa": 3
            },
            "cardinalities": {
                "cat": 4
            },
            "argn_processor": "tgt",
            "argn_table": "t4",
            "argn_column": "c4"
        },
        "card_number": {
            "encoding_type": "TABULAR_CHARACTER",
            "has_nan": false,
            "max_string_length": 19,
            "codes": {
                "P0": {
                    "\u0000": 0,
                    "*": 1
                },
                "P1": {
                    "\u0000": 0,
                    "*": 1
                },
                "P2": {
                    "\u0000": 0,
                    "*": 1
                },
                "P3": {
                    "\u0000": 0,
                    "*": 1
                },
                "P4": {
                    "\u0000": 0,
                    " ": 1
                },
                "P5": {
                    "\u0000": 0,
                    "*": 1
                },
                "P6": {
                    "\u0000": 0,
                    "*": 1
                },
                "P7": {
                    "\u0000": 0,
                    "*": 1
                },
                "P8": {
                    "\u0000": 0,
                    "*": 1
                },
                "P9": {
                    "\u0000": 0,
                    " ": 1
                },
                "P10": {
                    "\u0000": 0,
                    "*": 1
                },
                "P11": {
                    "\u0000": 0,
                    "*": 1
                },
                "P12": {
                    "\u0000": 0,
                    "*": 1
                },
                "P13": {
                    "\u0000": 0,
                    "*": 1
                },
                "P14": {
                    "\u0000": 0,
                    " ": 1
                },
                "P15": {
                    "\u0000": 0,
                    "1": 1,
                    "2": 2,
                    "3": 3,
                    "4": 4,
                    "5": 5,
                    "6": 6,
                    "7": 7,
                    "8": 8,
                    "9": 9
                },
                "P16": {
                    "\u0000": 0,
                    "0": 1,
                    "1": 2,
                    "2": 3,
                    "3": 4,
                    "4": 5,
                    "5": 6,
                    "6": 7,
                    "7": 8,
                    "8": 9,
                    "9": 10
                },
                "P17": {
                    "\u0000": 0,
                    "0": 1,
                    "1": 2,
                    "2": 3,
                    "3": 4,
                    "4": 5,
                    "5": 6,
                    "6": 7,
                    "7": 8,
                    "8": 9,
                    "9": 10
                },
                "P18": {
                    "\u0000": 0,
                    "0": 1,
                    "1": 2,
                    "2": 3,
                    "3": 4,
                    "4": 5,
                    "5": 6,
                    "6": 7,
                    "7": 8,
                    "8": 9,
                    "9": 10
                }
            },
            "cardinalities": {
                "P0": 2,
                "P1": 2,
                "P2": 2,
                "P3": 2,
                "P4": 2,
                "P5": 2,
                "P6": 2,
                "P7": 2,
                "P8": 2,
                "P9": 2,
                "P10": 2,
                "P11": 2,
                "P12": 2,
                "P13": 2,
                "P14": 2,
                "P15": 10,
                "P16": 11,
                "P17": 11,
                "P18": 11
            },
            "argn_processor": "tgt",
            "argn_table": "t5",
            "argn_column": "c5"
        },
        "expiry": {
            "value_protection": true,
            "encoding_type": "TABULAR_DATETIME",
            "cardinalities": {
                "year": 6,
                "month": 12,
                "day": 1
            },
            "has_nan": false,
            "has_time": false,
            "has_ms": false,
            "min_values": {
                "year": 2025,
                "month": 1,
                "day": 1,
                "hour": 0,
                "minute": 0,
                "second": 0,
                "ms_E2": 0,
                "ms_E1": 0,
                "ms_E0": 0
            },
            "max_values": {
                "year": 2030,
                "month": 12,
                "day": 1,
                "hour": 0,
                "minute": 0,
                "second": 0,
                "ms_E2": 0,
                "ms_E1": 0,
                "ms_E0": 0
            },
            "min": "2025-02-01",
            "max": "2030-12-01",
            "argn_processor": "tgt",
            "argn_table": "t6",
            "argn_column": "c6"
        },
        "status": {
            "value_protection": true,
            "encoding_type": "TABULAR_CATEGORICAL",
            "no_of_rare_categories": 0,
            "codes": {
                "_RARE_": 0,
                "Aktif": 1,
                "Bloke": 2,
                "Kapalı": 3
            },
            "cardinalities": {
                "cat": 4
            },
            "argn_processor": "tgt",
            "argn_table": "t7",
            "argn_column": "c7"
        },
        "issued_date": {
            "value_protection": true,
            "encoding_type": "TABULAR_DATETIME",
            "cardinalities": {
                "year": 5,
                "month": 12,
                "day": 31
            },
            "has_nan": false,
            "has_time": false,
            "has_ms": false,
            "min_values": {
                "year": 2019,
                "month": 1,
                "day": 1,
                "hour": 0,
                "minute": 0,
                "second": 0,
                "ms_E2": 0,
                "ms_E1": 0,
                "ms_E0": 0
            },
            "max_values": {
                "year": 2023,
                "month": 12,
                "day": 31,
                "hour": 0,
                "minute": 0,
                "second": 0,
                "ms_E2": 0,
                "ms_E1": 0,
                "ms_E0": 0
            },
            "min": "2019-03-17",
            "max": "2023-11-07",
            "argn_processor": "tgt",
            "argn_table": "t8",
            "argn_column": "c8"
        }
    },
    "no_of_training_records": 241,
    "no_of_validation_records": 59,
    "seq_len": {
        "min": 1,
        "max": 1,
        "median": 1,
        "value_protection": true
    },
    "is_sequential": false,
    "keys": {
        "primary_key": "card_id"
    },
    "value_protection_epsilon_spent": null
}